MANIFEST.in
README
setup.py
tesserwrap/__init__.py
tesserwrap/core.py
tesserwrap.egg-info/PKG-INFO
tesserwrap.egg-info/SOURCES.txt
tesserwrap.egg-info/dependency_links.txt
tesserwrap.egg-info/not-zip-safe
tesserwrap.egg-info/top_level.txt
tesserwrap/cpp/tesseract_ext.cpp
tesserwrap/cpp/tesseract_ext.h
tesserwrap/cpp/tesseract_wrap.cpp
tesserwrap/cpp/tesseract_wrap.h