Metadata-Version: 1.1
Name: tesserwrap
Version: 0.1.4
Summary: Basic python bindings to the Tesseract C++ API
Home-page: https://github.com/gregjurman/tesserwrap
Author: Greg Jurman, and others
Author-email: gdj2214@rit.edu
License: Apache License 2.0
Keywords: tesseract ocr cpp
Platform: UNKNOWN
Classifier: Topic :: Scientific/Engineering :: Image Recognition
Classifier: License :: OSI Approved :: Apache Software License
Classifier: Development Status :: 3 - Alpha
Classifier: Topic :: Software Development :: Libraries :: Python Modules
Classifier: Programming Language :: Python :: 2.7
Classifier: Programming Language :: Python :: 3.3
